{
    "1": [
        {
            "competition": "Championnats",
            "niveau": "DISTRICT LOT FOOTBALL",
            "poule": null,
            "division": "DIVISION 3",
            "date": "2019/09/08",
            "heure": "15:00",
            "domicile": "FRAYSSINET FC ",
            "exterieur": "F.F. MAUROUX ",
            "scoreDom": "1",
            "scoreExt": "2"
        },
        {
            "competition": "Championnats",
            "niveau": "DISTRICT LOT FOOTBALL",
            "poule": null,
            "division": "DIVISION 3",
            "date": "2019/09/08",
            "heure": "15:00",
            "domicile": "CAZALS-MONTCL 2",
            "exterieur": "QUERCY BLANC 2",
            "scoreDom": null,
            "scoreExt": null
        },
        {
            "competition": "Championnats",
            "niveau": "DISTRICT LOT FOOTBALL",
            "poule": null,
            "division": "DIVISION 3",
            "date": "2019/09/08",
            "heure": "15:00",
            "domicile": "ST MATRE-LE B ",
            "exterieur": "F.C. CAUSSE SUD 46 2",
            "scoreDom": "8",
            "scoreExt": "1"
        },
        {
            "competition": "Championnats",
            "niveau": "DISTRICT LOT FOOTBALL",
            "poule": null,
            "division": "DIVISION 3",
            "date": "2019/09/08",
            "heure": "15:00",
            "domicile": "LACAPELLE FOOTBALL 2",
            "exterieur": "MONTCABRIER 2",
            "scoreDom": "2",
            "scoreExt": "2"
        },
        {
            "competition": "Championnats",
            "niveau": "DISTRICT LOT FOOTBALL",
            "poule": null,
            "division": "DIVISION 3",
            "date": "2019/09/08",
            "heure": "15:00",
            "domicile": "ST PAUL LOUBR ",
            "exterieur": "THEDIRAC ",
            "scoreDom": "2",
            "scoreExt": "0"
        }
    ],
    "2": [
        {
            "competition": "Championnats",
            "niveau": "DISTRICT LOT FOOTBALL",
            "poule": null,
            "division": "DIVISION 3",
            "date": "2019/09/22",
            "heure": "13:00",
            "domicile": "QUERCY BLANC 2",
            "exterieur": "FRAYSSINET FC ",
            "scoreDom": null,
            "scoreExt": null
        },
        {
            "competition": "Championnats",
            "niveau": "DISTRICT LOT FOOTBALL",
            "poule": null,
            "division": "DIVISION 3",
            "date": "2019/09/22",
            "heure": "15:00",
            "domicile": "F.F. MAUROUX ",
            "exterieur": "ST MATRE-LE B ",
            "scoreDom": "0",
            "scoreExt": "4"
        },
        {
            "competition": "Championnats",
            "niveau": "DISTRICT LOT FOOTBALL",
            "poule": null,
            "division": "DIVISION 3",
            "date": "2019/09/22",
            "heure": "15:00",
            "domicile": "F.C. CAUSSE SUD 46 2",
            "exterieur": "LACAPELLE FOOTBALL 2",
            "scoreDom": "0",
            "scoreExt": "3"
        },
        {
            "competition": "Championnats",
            "niveau": "DISTRICT LOT FOOTBALL",
            "poule": null,
            "division": "DIVISION 3",
            "date": "2019/09/22",
            "heure": "15:00",
            "domicile": "THEDIRAC ",
            "exterieur": "CAZALS-MONTCL 2",
            "scoreDom": "3",
            "scoreExt": "2"
        },
        {
            "competition": "Championnats",
            "niveau": "DISTRICT LOT FOOTBALL",
            "poule": null,
            "division": "DIVISION 3",
            "date": "2019/09/22",
            "heure": "15:00",
            "domicile": "MONTCABRIER 2",
            "exterieur": "ST PAUL LOUBR ",
            "scoreDom": "3",
            "scoreExt": "0"
        }
    ],
    "3": [
        {
            "competition": "Championnats",
            "niveau": "DISTRICT LOT FOOTBALL",
            "poule": null,
            "division": "DIVISION 3",
            "date": "2019/10/06",
            "heure": "13:00",
            "domicile": "LACAPELLE FOOTBALL 2",
            "exterieur": "ST MATRE-LE B ",
            "scoreDom": "1",
            "scoreExt": "2"
        },
        {
            "competition": "Championnats",
            "niveau": "DISTRICT LOT FOOTBALL",
            "poule": null,
            "division": "DIVISION 3",
            "date": "2019/10/06",
            "heure": "15:00",
            "domicile": "F.F. MAUROUX ",
            "exterieur": "QUERCY BLANC 2",
            "scoreDom": null,
            "scoreExt": null
        },
        {
            "competition": "Championnats",
            "niveau": "DISTRICT LOT FOOTBALL",
            "poule": null,
            "division": "DIVISION 3",
            "date": "2019/10/06",
            "heure": "15:00",
            "domicile": "FRAYSSINET FC ",
            "exterieur": "THEDIRAC ",
            "scoreDom": "0",
            "scoreExt": "0"
        },
        {
            "competition": "Championnats",
            "niveau": "DISTRICT LOT FOOTBALL",
            "poule": null,
            "division": "DIVISION 3",
            "date": "2019/10/06",
            "heure": "15:00",
            "domicile": "CAZALS-MONTCL 2",
            "exterieur": "MONTCABRIER 2",
            "scoreDom": "2",
            "scoreExt": "5"
        },
        {
            "competition": "Championnats",
            "niveau": "DISTRICT LOT FOOTBALL",
            "poule": null,
            "division": "DIVISION 3",
            "date": "2019/10/06",
            "heure": "15:00",
            "domicile": "ST PAUL LOUBR ",
            "exterieur": "F.C. CAUSSE SUD 46 2",
            "scoreDom": "5",
            "scoreExt": "1"
        }
    ],
    "4": [
        {
            "competition": "Championnats",
            "niveau": "DISTRICT LOT FOOTBALL",
            "poule": null,
            "division": "DIVISION 3",
            "date": "2019/10/20",
            "heure": "15:00",
            "domicile": "F.C. CAUSSE SUD 46 2",
            "exterieur": "CAZALS-MONTCL 2",
            "scoreDom": "1",
            "scoreExt": "1"
        },
        {
            "competition": "Championnats",
            "niveau": "DISTRICT LOT FOOTBALL",
            "poule": null,
            "division": "DIVISION 3",
            "date": "2019/10/20",
            "heure": "15:00",
            "domicile": "ST MATRE-LE B ",
            "exterieur": "ST PAUL LOUBR ",
            "scoreDom": "6",
            "scoreExt": "0"
        },
        {
            "competition": "Championnats",
            "niveau": "DISTRICT LOT FOOTBALL",
            "poule": null,
            "division": "DIVISION 3",
            "date": "2019/10/20",
            "heure": "15:00",
            "domicile": "LACAPELLE FOOTBALL 2",
            "exterieur": "F.F. MAUROUX ",
            "scoreDom": "2",
            "scoreExt": "0"
        },
        {
            "competition": "Championnats",
            "niveau": "DISTRICT LOT FOOTBALL",
            "poule": null,
            "division": "DIVISION 3",
            "date": "2019/10/20",
            "heure": "15:00",
            "domicile": "MONTCABRIER 2",
            "exterieur": "FRAYSSINET FC ",
            "scoreDom": "1",
            "scoreExt": "1"
        },
        {
            "competition": "Championnats",
            "niveau": "DISTRICT LOT FOOTBALL",
            "poule": null,
            "division": "DIVISION 3",
            "date": "2019/10/20",
            "heure": "15:00",
            "domicile": "THEDIRAC ",
            "exterieur": "QUERCY BLANC 2",
            "scoreDom": null,
            "scoreExt": null
        }
    ],
    "5": [
        {
            "competition": "Championnats",
            "niveau": "DISTRICT LOT FOOTBALL",
            "poule": null,
            "division": "DIVISION 3",
            "date": "2019/11/03",
            "heure": "15:00",
            "domicile": "FRAYSSINET FC ",
            "exterieur": "F.C. CAUSSE SUD 46 2",
            "scoreDom": "2",
            "scoreExt": "1"
        },
        {
            "competition": "Championnats",
            "niveau": "DISTRICT LOT FOOTBALL",
            "poule": null,
            "division": "DIVISION 3",
            "date": "2019/11/03",
            "heure": "15:00",
            "domicile": "ST PAUL LOUBR ",
            "exterieur": "LACAPELLE FOOTBALL 2",
            "scoreDom": "0",
            "scoreExt": "1"
        },
        {
            "competition": "Championnats",
            "niveau": "DISTRICT LOT FOOTBALL",
            "poule": null,
            "division": "DIVISION 3",
            "date": "2019/11/03",
            "heure": "15:00",
            "domicile": "F.F. MAUROUX ",
            "exterieur": "THEDIRAC ",
            "scoreDom": "1",
            "scoreExt": "2"
        },
        {
            "competition": "Championnats",
            "niveau": "DISTRICT LOT FOOTBALL",
            "poule": null,
            "division": "DIVISION 3",
            "date": "2019/12/15",
            "heure": "15:00",
            "domicile": "QUERCY BLANC 2",
            "exterieur": "MONTCABRIER 2",
            "scoreDom": null,
            "scoreExt": null
        },
        {
            "competition": "Championnats",
            "niveau": "DISTRICT LOT FOOTBALL",
            "poule": null,
            "division": "DIVISION 3",
            "date": "2020/01/05",
            "heure": "13:00",
            "domicile": "CAZALS-MONTCL 2",
            "exterieur": "ST MATRE-LE B ",
            "scoreDom": "2",
            "scoreExt": "3"
        }
    ],
    "6": [
        {
            "competition": "Championnats",
            "niveau": "DISTRICT LOT FOOTBALL",
            "poule": null,
            "division": "DIVISION 3",
            "date": "2019/12/22",
            "heure": "15:00",
            "domicile": "ST MATRE-LE B ",
            "exterieur": "FRAYSSINET FC ",
            "scoreDom": "4",
            "scoreExt": "0"
        },
        {
            "competition": "Championnats",
            "niveau": "DISTRICT LOT FOOTBALL",
            "poule": null,
            "division": "DIVISION 3",
            "date": "2019/12/22",
            "heure": "15:00",
            "domicile": "F.C. CAUSSE SUD 46 2",
            "exterieur": "QUERCY BLANC 2",
            "scoreDom": null,
            "scoreExt": null
        },
        {
            "competition": "Championnats",
            "niveau": "DISTRICT LOT FOOTBALL",
            "poule": null,
            "division": "DIVISION 3",
            "date": "2020/01/05",
            "heure": "15:00",
            "domicile": "MONTCABRIER 2",
            "exterieur": "THEDIRAC ",
            "scoreDom": "3",
            "scoreExt": "1"
        },
        {
            "competition": "Championnats",
            "niveau": "DISTRICT LOT FOOTBALL",
            "poule": null,
            "division": "DIVISION 3",
            "date": "2020/01/12",
            "heure": "15:00",
            "domicile": "LACAPELLE FOOTBALL 2",
            "exterieur": "CAZALS-MONTCL 2",
            "scoreDom": "5",
            "scoreExt": "3"
        },
        {
            "competition": "Championnats",
            "niveau": "DISTRICT LOT FOOTBALL",
            "poule": null,
            "division": "DIVISION 3",
            "date": "2020/01/12",
            "heure": "15:00",
            "domicile": "ST PAUL LOUBR ",
            "exterieur": "F.F. MAUROUX ",
            "scoreDom": "4",
            "scoreExt": "1"
        }
    ],
    "7": [
        {
            "competition": "Championnats",
            "niveau": "DISTRICT LOT FOOTBALL",
            "poule": null,
            "division": "DIVISION 3",
            "date": "2019/11/24",
            "heure": "13:00",
            "domicile": "QUERCY BLANC 2",
            "exterieur": "ST MATRE-LE B ",
            "scoreDom": null,
            "scoreExt": null
        },
        {
            "competition": "Championnats",
            "niveau": "DISTRICT LOT FOOTBALL",
            "poule": null,
            "division": "DIVISION 3",
            "date": "2019/11/24",
            "heure": "13:00",
            "domicile": "CAZALS-MONTCL 2",
            "exterieur": "ST PAUL LOUBR ",
            "scoreDom": "3",
            "scoreExt": "6"
        },
        {
            "competition": "Championnats",
            "niveau": "DISTRICT LOT FOOTBALL",
            "poule": null,
            "division": "DIVISION 3",
            "date": "2019/11/24",
            "heure": "15:00",
            "domicile": "THEDIRAC ",
            "exterieur": "F.C. CAUSSE SUD 46 2",
            "scoreDom": "6",
            "scoreExt": "0"
        },
        {
            "competition": "Championnats",
            "niveau": "DISTRICT LOT FOOTBALL",
            "poule": null,
            "division": "DIVISION 3",
            "date": "2019/11/24",
            "heure": "15:00",
            "domicile": "FRAYSSINET FC ",
            "exterieur": "LACAPELLE FOOTBALL 2",
            "scoreDom": "2",
            "scoreExt": "2"
        },
        {
            "competition": "Championnats",
            "niveau": "DISTRICT LOT FOOTBALL",
            "poule": null,
            "division": "DIVISION 3",
            "date": "2019/11/24",
            "heure": "15:00",
            "domicile": "F.F. MAUROUX ",
            "exterieur": "MONTCABRIER 2",
            "scoreDom": "2",
            "scoreExt": "5"
        }
    ],
    "8": [
        {
            "competition": "Championnats",
            "niveau": "DISTRICT LOT FOOTBALL",
            "poule": null,
            "division": "DIVISION 3",
            "date": "2019/12/01",
            "heure": "15:00",
            "domicile": "CAZALS-MONTCL 2",
            "exterieur": "F.F. MAUROUX ",
            "scoreDom": "1",
            "scoreExt": "2"
        },
        {
            "competition": "Championnats",
            "niveau": "DISTRICT LOT FOOTBALL",
            "poule": null,
            "division": "DIVISION 3",
            "date": "2019/12/01",
            "heure": "15:00",
            "domicile": "ST MATRE-LE B ",
            "exterieur": "THEDIRAC ",
            "scoreDom": "3",
            "scoreExt": "1"
        },
        {
            "competition": "Championnats",
            "niveau": "DISTRICT LOT FOOTBALL",
            "poule": null,
            "division": "DIVISION 3",
            "date": "2019/12/01",
            "heure": "15:00",
            "domicile": "ST PAUL LOUBR ",
            "exterieur": "FRAYSSINET FC ",
            "scoreDom": "4",
            "scoreExt": "1"
        },
        {
            "competition": "Championnats",
            "niveau": "DISTRICT LOT FOOTBALL",
            "poule": null,
            "division": "DIVISION 3",
            "date": "2019/12/01",
            "heure": "15:00",
            "domicile": "LACAPELLE FOOTBALL 2",
            "exterieur": "QUERCY BLANC 2",
            "scoreDom": null,
            "scoreExt": null
        },
        {
            "competition": "Championnats",
            "niveau": "DISTRICT LOT FOOTBALL",
            "poule": null,
            "division": "DIVISION 3",
            "date": "2019/12/01",
            "heure": "15:00",
            "domicile": "F.C. CAUSSE SUD 46 2",
            "exterieur": "MONTCABRIER 2",
            "scoreDom": "1",
            "scoreExt": "2"
        }
    ],
    "9": [
        {
            "competition": "Championnats",
            "niveau": "DISTRICT LOT FOOTBALL",
            "poule": null,
            "division": "DIVISION 3",
            "date": "2019/12/08",
            "heure": "15:00",
            "domicile": "F.F. MAUROUX ",
            "exterieur": "F.C. CAUSSE SUD 46 2",
            "scoreDom": "3",
            "scoreExt": "0"
        },
        {
            "competition": "Championnats",
            "niveau": "DISTRICT LOT FOOTBALL",
            "poule": null,
            "division": "DIVISION 3",
            "date": "2019/12/08",
            "heure": "15:00",
            "domicile": "MONTCABRIER 2",
            "exterieur": "ST MATRE-LE B ",
            "scoreDom": "2",
            "scoreExt": "7"
        },
        {
            "competition": "Championnats",
            "niveau": "DISTRICT LOT FOOTBALL",
            "poule": null,
            "division": "DIVISION 3",
            "date": "2019/12/08",
            "heure": "15:00",
            "domicile": "THEDIRAC ",
            "exterieur": "LACAPELLE FOOTBALL 2",
            "scoreDom": "3",
            "scoreExt": "1"
        },
        {
            "competition": "Championnats",
            "niveau": "DISTRICT LOT FOOTBALL",
            "poule": null,
            "division": "DIVISION 3",
            "date": "2019/12/08",
            "heure": "15:00",
            "domicile": "FRAYSSINET FC ",
            "exterieur": "CAZALS-MONTCL 2",
            "scoreDom": "3",
            "scoreExt": "3"
        },
        {
            "competition": "Championnats",
            "niveau": "DISTRICT LOT FOOTBALL",
            "poule": null,
            "division": "DIVISION 3",
            "date": "2020/01/05",
            "heure": "13:00",
            "domicile": "QUERCY BLANC 2",
            "exterieur": "ST PAUL LOUBR ",
            "scoreDom": null,
            "scoreExt": null
        }
    ],
    "10": [
        {
            "competition": "Championnats",
            "niveau": "DISTRICT LOT FOOTBALL",
            "poule": null,
            "division": "DIVISION 3",
            "date": "2020/02/02",
            "heure": "13:00",
            "domicile": "QUERCY BLANC 2",
            "exterieur": "CAZALS-MONTCL 2",
            "scoreDom": null,
            "scoreExt": null
        },
        {
            "competition": "Championnats",
            "niveau": "DISTRICT LOT FOOTBALL",
            "poule": null,
            "division": "DIVISION 3",
            "date": "2020/02/02",
            "heure": "15:00",
            "domicile": "F.F. MAUROUX ",
            "exterieur": "FRAYSSINET FC ",
            "scoreDom": null,
            "scoreExt": null
        },
        {
            "competition": "Championnats",
            "niveau": "DISTRICT LOT FOOTBALL",
            "poule": null,
            "division": "DIVISION 3",
            "date": "2020/02/02",
            "heure": "15:00",
            "domicile": "F.C. CAUSSE SUD 46 2",
            "exterieur": "ST MATRE-LE B ",
            "scoreDom": null,
            "scoreExt": null
        },
        {
            "competition": "Championnats",
            "niveau": "DISTRICT LOT FOOTBALL",
            "poule": null,
            "division": "DIVISION 3",
            "date": "2020/02/02",
            "heure": "15:00",
            "domicile": "MONTCABRIER 2",
            "exterieur": "LACAPELLE FOOTBALL 2",
            "scoreDom": null,
            "scoreExt": null
        },
        {
            "competition": "Championnats",
            "niveau": "DISTRICT LOT FOOTBALL",
            "poule": null,
            "division": "DIVISION 3",
            "date": "2020/02/02",
            "heure": "15:00",
            "domicile": "THEDIRAC ",
            "exterieur": "ST PAUL LOUBR ",
            "scoreDom": null,
            "scoreExt": null
        }
    ],
    "11": [
        {
            "competition": "Championnats",
            "niveau": "DISTRICT LOT FOOTBALL",
            "poule": null,
            "division": "DIVISION 3",
            "date": "2020/02/09",
            "heure": "15:00",
            "domicile": "LACAPELLE FOOTBALL 2",
            "exterieur": "F.C. CAUSSE SUD 46 2",
            "scoreDom": null,
            "scoreExt": null
        },
        {
            "competition": "Championnats",
            "niveau": "DISTRICT LOT FOOTBALL",
            "poule": null,
            "division": "DIVISION 3",
            "date": "2020/02/09",
            "heure": "15:00",
            "domicile": "FRAYSSINET FC ",
            "exterieur": "QUERCY BLANC 2",
            "scoreDom": null,
            "scoreExt": null
        },
        {
            "competition": "Championnats",
            "niveau": "DISTRICT LOT FOOTBALL",
            "poule": null,
            "division": "DIVISION 3",
            "date": "2020/02/09",
            "heure": "15:00",
            "domicile": "ST PAUL LOUBR ",
            "exterieur": "MONTCABRIER 2",
            "scoreDom": null,
            "scoreExt": null
        },
        {
            "competition": "Championnats",
            "niveau": "DISTRICT LOT FOOTBALL",
            "poule": null,
            "division": "DIVISION 3",
            "date": "2020/02/09",
            "heure": "15:00",
            "domicile": "CAZALS-MONTCL 2",
            "exterieur": "THEDIRAC ",
            "scoreDom": null,
            "scoreExt": null
        },
        {
            "competition": "Championnats",
            "niveau": "DISTRICT LOT FOOTBALL",
            "poule": null,
            "division": "DIVISION 3",
            "date": "2020/02/09",
            "heure": "15:00",
            "domicile": "ST MATRE-LE B ",
            "exterieur": "F.F. MAUROUX ",
            "scoreDom": null,
            "scoreExt": null
        }
    ],
    "12": [
        {
            "competition": "Championnats",
            "niveau": "DISTRICT LOT FOOTBALL",
            "poule": null,
            "division": "DIVISION 3",
            "date": "2020/02/23",
            "heure": "13:00",
            "domicile": "QUERCY BLANC 2",
            "exterieur": "F.F. MAUROUX ",
            "scoreDom": null,
            "scoreExt": null
        },
        {
            "competition": "Championnats",
            "niveau": "DISTRICT LOT FOOTBALL",
            "poule": null,
            "division": "DIVISION 3",
            "date": "2020/02/23",
            "heure": "15:00",
            "domicile": "ST MATRE-LE B ",
            "exterieur": "LACAPELLE FOOTBALL 2",
            "scoreDom": null,
            "scoreExt": null
        },
        {
            "competition": "Championnats",
            "niveau": "DISTRICT LOT FOOTBALL",
            "poule": null,
            "division": "DIVISION 3",
            "date": "2020/02/23",
            "heure": "15:00",
            "domicile": "F.C. CAUSSE SUD 46 2",
            "exterieur": "ST PAUL LOUBR ",
            "scoreDom": null,
            "scoreExt": null
        },
        {
            "competition": "Championnats",
            "niveau": "DISTRICT LOT FOOTBALL",
            "poule": null,
            "division": "DIVISION 3",
            "date": "2020/02/23",
            "heure": "15:00",
            "domicile": "THEDIRAC ",
            "exterieur": "FRAYSSINET FC ",
            "scoreDom": null,
            "scoreExt": null
        },
        {
            "competition": "Championnats",
            "niveau": "DISTRICT LOT FOOTBALL",
            "poule": null,
            "division": "DIVISION 3",
            "date": "2020/02/23",
            "heure": "15:00",
            "domicile": "MONTCABRIER 2",
            "exterieur": "CAZALS-MONTCL 2",
            "scoreDom": null,
            "scoreExt": null
        }
    ],
    "13": [
        {
            "competition": "Championnats",
            "niveau": "DISTRICT LOT FOOTBALL",
            "poule": null,
            "division": "DIVISION 3",
            "date": "2020/03/01",
            "heure": "15:00",
            "domicile": "CAZALS-MONTCL 2",
            "exterieur": "F.C. CAUSSE SUD 46 2",
            "scoreDom": null,
            "scoreExt": null
        },
        {
            "competition": "Championnats",
            "niveau": "DISTRICT LOT FOOTBALL",
            "poule": null,
            "division": "DIVISION 3",
            "date": "2020/03/01",
            "heure": "15:00",
            "domicile": "F.F. MAUROUX ",
            "exterieur": "LACAPELLE FOOTBALL 2",
            "scoreDom": null,
            "scoreExt": null
        },
        {
            "competition": "Championnats",
            "niveau": "DISTRICT LOT FOOTBALL",
            "poule": null,
            "division": "DIVISION 3",
            "date": "2020/03/01",
            "heure": "15:00",
            "domicile": "ST PAUL LOUBR ",
            "exterieur": "ST MATRE-LE B ",
            "scoreDom": null,
            "scoreExt": null
        },
        {
            "competition": "Championnats",
            "niveau": "DISTRICT LOT FOOTBALL",
            "poule": null,
            "division": "DIVISION 3",
            "date": "2020/03/01",
            "heure": "15:00",
            "domicile": "FRAYSSINET FC ",
            "exterieur": "MONTCABRIER 2",
            "scoreDom": null,
            "scoreExt": null
        },
        {
            "competition": "Championnats",
            "niveau": "DISTRICT LOT FOOTBALL",
            "poule": null,
            "division": "DIVISION 3",
            "date": "2020/03/01",
            "heure": "15:00",
            "domicile": "QUERCY BLANC 2",
            "exterieur": "THEDIRAC ",
            "scoreDom": null,
            "scoreExt": null
        }
    ],
    "14": [
        {
            "competition": "Championnats",
            "niveau": "DISTRICT LOT FOOTBALL",
            "poule": null,
            "division": "DIVISION 3",
            "date": "2020/03/08",
            "heure": "15:00",
            "domicile": "ST MATRE-LE B ",
            "exterieur": "CAZALS-MONTCL 2",
            "scoreDom": null,
            "scoreExt": null
        },
        {
            "competition": "Championnats",
            "niveau": "DISTRICT LOT FOOTBALL",
            "poule": null,
            "division": "DIVISION 3",
            "date": "2020/03/08",
            "heure": "15:00",
            "domicile": "THEDIRAC ",
            "exterieur": "F.F. MAUROUX ",
            "scoreDom": null,
            "scoreExt": null
        },
        {
            "competition": "Championnats",
            "niveau": "DISTRICT LOT FOOTBALL",
            "poule": null,
            "division": "DIVISION 3",
            "date": "2020/03/08",
            "heure": "15:00",
            "domicile": "F.C. CAUSSE SUD 46 2",
            "exterieur": "FRAYSSINET FC ",
            "scoreDom": null,
            "scoreExt": null
        },
        {
            "competition": "Championnats",
            "niveau": "DISTRICT LOT FOOTBALL",
            "poule": null,
            "division": "DIVISION 3",
            "date": "2020/03/08",
            "heure": "15:00",
            "domicile": "LACAPELLE FOOTBALL 2",
            "exterieur": "ST PAUL LOUBR ",
            "scoreDom": null,
            "scoreExt": null
        },
        {
            "competition": "Championnats",
            "niveau": "DISTRICT LOT FOOTBALL",
            "poule": null,
            "division": "DIVISION 3",
            "date": "2020/03/08",
            "heure": "15:00",
            "domicile": "MONTCABRIER 2",
            "exterieur": "QUERCY BLANC 2",
            "scoreDom": null,
            "scoreExt": null
        }
    ],
    "15": [
        {
            "competition": "Championnats",
            "niveau": "DISTRICT LOT FOOTBALL",
            "poule": null,
            "division": "DIVISION 3",
            "date": "2020/03/22",
            "heure": "13:00",
            "domicile": "QUERCY BLANC 2",
            "exterieur": "F.C. CAUSSE SUD 46 2",
            "scoreDom": null,
            "scoreExt": null
        },
        {
            "competition": "Championnats",
            "niveau": "DISTRICT LOT FOOTBALL",
            "poule": null,
            "division": "DIVISION 3",
            "date": "2020/03/22",
            "heure": "15:00",
            "domicile": "FRAYSSINET FC ",
            "exterieur": "ST MATRE-LE B ",
            "scoreDom": null,
            "scoreExt": null
        },
        {
            "competition": "Championnats",
            "niveau": "DISTRICT LOT FOOTBALL",
            "poule": null,
            "division": "DIVISION 3",
            "date": "2020/03/22",
            "heure": "15:00",
            "domicile": "CAZALS-MONTCL 2",
            "exterieur": "LACAPELLE FOOTBALL 2",
            "scoreDom": null,
            "scoreExt": null
        },
        {
            "competition": "Championnats",
            "niveau": "DISTRICT LOT FOOTBALL",
            "poule": null,
            "division": "DIVISION 3",
            "date": "2020/03/22",
            "heure": "15:00",
            "domicile": "THEDIRAC ",
            "exterieur": "MONTCABRIER 2",
            "scoreDom": null,
            "scoreExt": null
        },
        {
            "competition": "Championnats",
            "niveau": "DISTRICT LOT FOOTBALL",
            "poule": null,
            "division": "DIVISION 3",
            "date": "2020/03/22",
            "heure": "15:00",
            "domicile": "F.F. MAUROUX ",
            "exterieur": "ST PAUL LOUBR ",
            "scoreDom": null,
            "scoreExt": null
        }
    ],
    "16": [
        {
            "competition": "Championnats",
            "niveau": "DISTRICT LOT FOOTBALL",
            "poule": null,
            "division": "DIVISION 3",
            "date": "2020/03/29",
            "heure": "13:00",
            "domicile": "MONTCABRIER 2",
            "exterieur": "F.F. MAUROUX ",
            "scoreDom": null,
            "scoreExt": null
        },
        {
            "competition": "Championnats",
            "niveau": "DISTRICT LOT FOOTBALL",
            "poule": null,
            "division": "DIVISION 3",
            "date": "2020/03/29",
            "heure": "15:00",
            "domicile": "LACAPELLE FOOTBALL 2",
            "exterieur": "FRAYSSINET FC ",
            "scoreDom": null,
            "scoreExt": null
        },
        {
            "competition": "Championnats",
            "niveau": "DISTRICT LOT FOOTBALL",
            "poule": null,
            "division": "DIVISION 3",
            "date": "2020/03/29",
            "heure": "15:00",
            "domicile": "ST PAUL LOUBR ",
            "exterieur": "CAZALS-MONTCL 2",
            "scoreDom": null,
            "scoreExt": null
        },
        {
            "competition": "Championnats",
            "niveau": "DISTRICT LOT FOOTBALL",
            "poule": null,
            "division": "DIVISION 3",
            "date": "2020/03/29",
            "heure": "15:00",
            "domicile": "ST MATRE-LE B ",
            "exterieur": "QUERCY BLANC 2",
            "scoreDom": null,
            "scoreExt": null
        },
        {
            "competition": "Championnats",
            "niveau": "DISTRICT LOT FOOTBALL",
            "poule": null,
            "division": "DIVISION 3",
            "date": "2020/03/29",
            "heure": "15:00",
            "domicile": "F.C. CAUSSE SUD 46 2",
            "exterieur": "THEDIRAC ",
            "scoreDom": null,
            "scoreExt": null
        }
    ],
    "17": [
        {
            "competition": "Championnats",
            "niveau": "DISTRICT LOT FOOTBALL",
            "poule": null,
            "division": "DIVISION 3",
            "date": "2020/04/19",
            "heure": "13:00",
            "domicile": "QUERCY BLANC 2",
            "exterieur": "LACAPELLE FOOTBALL 2",
            "scoreDom": null,
            "scoreExt": null
        },
        {
            "competition": "Championnats",
            "niveau": "DISTRICT LOT FOOTBALL",
            "poule": null,
            "division": "DIVISION 3",
            "date": "2020/04/19",
            "heure": "15:00",
            "domicile": "THEDIRAC ",
            "exterieur": "ST MATRE-LE B ",
            "scoreDom": null,
            "scoreExt": null
        },
        {
            "competition": "Championnats",
            "niveau": "DISTRICT LOT FOOTBALL",
            "poule": null,
            "division": "DIVISION 3",
            "date": "2020/04/19",
            "heure": "15:00",
            "domicile": "FRAYSSINET FC ",
            "exterieur": "ST PAUL LOUBR ",
            "scoreDom": null,
            "scoreExt": null
        },
        {
            "competition": "Championnats",
            "niveau": "DISTRICT LOT FOOTBALL",
            "poule": null,
            "division": "DIVISION 3",
            "date": "2020/04/19",
            "heure": "15:00",
            "domicile": "MONTCABRIER 2",
            "exterieur": "F.C. CAUSSE SUD 46 2",
            "scoreDom": null,
            "scoreExt": null
        },
        {
            "competition": "Championnats",
            "niveau": "DISTRICT LOT FOOTBALL",
            "poule": null,
            "division": "DIVISION 3",
            "date": "2020/04/19",
            "heure": "15:00",
            "domicile": "F.F. MAUROUX ",
            "exterieur": "CAZALS-MONTCL 2",
            "scoreDom": null,
            "scoreExt": null
        }
    ],
    "18": [
        {
            "competition": "Championnats",
            "niveau": "DISTRICT LOT FOOTBALL",
            "poule": null,
            "division": "DIVISION 3",
            "date": "2020/04/26",
            "heure": "15:00",
            "domicile": "CAZALS-MONTCL 2",
            "exterieur": "FRAYSSINET FC ",
            "scoreDom": null,
            "scoreExt": null
        },
        {
            "competition": "Championnats",
            "niveau": "DISTRICT LOT FOOTBALL",
            "poule": null,
            "division": "DIVISION 3",
            "date": "2020/04/26",
            "heure": "15:00",
            "domicile": "ST PAUL LOUBR ",
            "exterieur": "QUERCY BLANC 2",
            "scoreDom": null,
            "scoreExt": null
        },
        {
            "competition": "Championnats",
            "niveau": "DISTRICT LOT FOOTBALL",
            "poule": null,
            "division": "DIVISION 3",
            "date": "2020/04/26",
            "heure": "15:00",
            "domicile": "ST MATRE-LE B ",
            "exterieur": "MONTCABRIER 2",
            "scoreDom": null,
            "scoreExt": null
        },
        {
            "competition": "Championnats",
            "niveau": "DISTRICT LOT FOOTBALL",
            "poule": null,
            "division": "DIVISION 3",
            "date": "2020/04/26",
            "heure": "15:00",
            "domicile": "LACAPELLE FOOTBALL 2",
            "exterieur": "THEDIRAC ",
            "scoreDom": null,
            "scoreExt": null
        },
        {
            "competition": "Championnats",
            "niveau": "DISTRICT LOT FOOTBALL",
            "poule": null,
            "division": "DIVISION 3",
            "date": "2020/04/26",
            "heure": "15:00",
            "domicile": "F.C. CAUSSE SUD 46 2",
            "exterieur": "F.F. MAUROUX ",
            "scoreDom": null,
            "scoreExt": null
        }
    ]
}